wsctrl/__init__.py
wsctrl/exceptions.py
wsctrl/sink_ctrl.py
wsctrl-1.0.2.dist-info/METADATA
wsctrl-1.0.2.dist-info/WHEEL
wsctrl-1.0.2.dist-info/licenses/LICENSE
wsctrl-1.0.2.dist-info/RECORD
